LICENSE
MANIFEST.in
README.md
setup.cfg
setup.py
symmetry/__init__.py
symmetry/groups.py
symmetry/symm_data.json
symmetry.egg-info/PKG-INFO
symmetry.egg-info/SOURCES.txt
symmetry.egg-info/dependency_links.txt
symmetry.egg-info/requires.txt
symmetry.egg-info/top_level.txt
symmetry/tests/__init__.py
symmetry/tests/test_groups.py