Metadata-Version: 1.1
Name: symmetry
Version: 0.1
Summary: Symmetry is a library for materials symmetry analysis.
Home-page: UNKNOWN
Author: Shyue Ping Ong
Author-email: ongsp@ucsd.edu
License: BSD
Keywords: crystallography,materials,symmetry,crystals
Platform: UNKNOWN
Classifier: Programming Language :: Python :: 2.7
Classifier: Development Status :: 4 - Beta
Classifier: Intended Audience :: Science/Research
Classifier: License :: OSI Approved :: BSD License
Classifier: Operating System :: OS Independent
Classifier: Topic :: Scientific/Engineering :: Physics
Classifier: Topic :: Scientific/Engineering :: Chemistry
